{"version":1,"resource":"file:///home/anirudhkailaje/Documents/01_UPenn/01_ESE5460/03_Project/ptb-xl-a-large-publicly-available-electrocardiography-dataset-1.0.1/Data_Loading.ipynb","entries":[{"id":"xl2W.ipynb","source":"edit","timestamp":1702169374394},{"id":"f4nP.ipynb","source":"edit","timestamp":1702170642629},{"id":"jbpV.ipynb","source":"edit","timestamp":1702170706970},{"id":"JAfM.ipynb","source":"edit","timestamp":1702170722042},{"id":"rMja.ipynb","source":"edit","timestamp":1702170836268},{"id":"1hLA.ipynb","source":"edit","timestamp":1702310046591},{"id":"I49H.ipynb","source":"edit","timestamp":1702335063739},{"id":"qLNh.ipynb","timestamp":1702335156624},{"id":"qZjB.ipynb","timestamp":1702335209837},{"id":"PbfH.ipynb","source":"edit","timestamp":1702335601293},{"id":"Llwy.ipynb","timestamp":1702403293202},{"id":"km0H.ipynb","timestamp":1702403310503},{"id":"8lcL.ipynb","timestamp":1702407157610},{"id":"Yqd6.ipynb","timestamp":1702407235711},{"id":"tFO4.ipynb","timestamp":1702407257419},{"id":"mxm9.ipynb","timestamp":1702407302968},{"id":"ZD09.ipynb","timestamp":1702407375076},{"id":"VQDO.ipynb","timestamp":1702410810937},{"id":"JCQ3.ipynb","source":"edit","timestamp":1702411010804},{"id":"rwAd.ipynb","source":"Update Notebook Metadata","timestamp":1702411019964},{"id":"HeuP.ipynb","source":"Update Notebook Metadata","timestamp":1702411083609},{"id":"AXka.ipynb","source":"Update Notebook Metadata","timestamp":1702411109793},{"id":"KAJP.ipynb","source":"Update Notebook Metadata","timestamp":1702411120053},{"id":"raoi.ipynb","source":"Insert Cell","timestamp":1702411488100},{"id":"Gw29.ipynb","source":"Insert Cell","timestamp":1702411520962},{"id":"Id6E.ipynb","source":"Insert Cell","timestamp":1702411563594},{"id":"rh7D.ipynb","source":"Insert Cell","timestamp":1702411619050},{"id":"Ati7.ipynb","source":"Insert Cell","timestamp":1702411694347},{"id":"GYhn.ipynb","source":"Insert Cell","timestamp":1702411806664},{"id":"7Yip.ipynb","source":"Insert Cell","timestamp":1702412970840},{"id":"5mUu.ipynb","timestamp":1702688114091},{"id":"jBIW.ipynb","timestamp":1702688173104},{"id":"lcZF.ipynb","source":"edit","timestamp":1702734174838},{"id":"uuIu.ipynb","source":"edit","timestamp":1702844966335},{"id":"u0zY.ipynb","timestamp":1702856986836},{"id":"oNH1.ipynb","timestamp":1702857000780},{"id":"QYrc.ipynb","timestamp":1702857019768},{"id":"KPCh.ipynb","timestamp":1702857086433},{"id":"GA9H.ipynb","source":"Insert Cell","timestamp":1702857088725},{"id":"MxQp.ipynb","source":"Insert Cell","timestamp":1702857113933},{"id":"uHOQ.ipynb","source":"Insert Cell","timestamp":1702857131914},{"id":"N3CE.ipynb","source":"Insert Cell","timestamp":1702857157938},{"id":"R7kg.ipynb","source":"Insert Cell","timestamp":1702857184526},{"id":"LBIe.ipynb","source":"Insert Cell","timestamp":1702857201814},{"id":"9dQQ.ipynb","source":"Insert Cell","timestamp":1702857234267},{"id":"IdXY.ipynb","source":"Insert Cell","timestamp":1702857423029},{"id":"JxKr.ipynb","source":"Insert Cell","timestamp":1702857827165},{"id":"wa9X.ipynb","source":"Insert Cell","timestamp":1702857898298},{"id":"hrmj.ipynb","source":"Insert Cell","timestamp":1702857943623},{"id":"6YXW.ipynb","source":"Insert Cell","timestamp":1702857985299}]}