{"version":1,"resource":"file:///home/anirudhkailaje/Documents/01_UPenn/01_ESE5460/03_Project/src/CNN_Trial.ipynb","entries":[{"id":"SiSU.ipynb","source":"Insert Cell","timestamp":1701290134081},{"id":"djOG.ipynb","source":"Insert Cell","timestamp":1701290265430},{"id":"EoQk.ipynb","source":"edit","timestamp":1701290272866},{"id":"VQ1H.ipynb","source":"edit","timestamp":1701290303238},{"id":"Db7O.ipynb","source":"edit","timestamp":1701290323923},{"id":"kZOn.ipynb","source":"edit","timestamp":1701290345747},{"id":"ECgB.ipynb","source":"edit","timestamp":1701290410720},{"id":"Wih8.ipynb","source":"edit","timestamp":1701290526189},{"id":"5fDD.ipynb","source":"edit","timestamp":1701290542925},{"id":"3gWv.ipynb","source":"edit","timestamp":1701290573417},{"id":"qEJM.ipynb","source":"edit","timestamp":1701290602654},{"id":"QGmH.ipynb","source":"edit","timestamp":1701290654562},{"id":"Ie10.ipynb","source":"edit","timestamp":1701290691374},{"id":"sO5H.ipynb","source":"edit","timestamp":1701290714387},{"id":"J5ZU.ipynb","source":"edit","timestamp":1701290726311},{"id":"rgac.ipynb","source":"edit","timestamp":1701290737707},{"id":"28wo.ipynb","source":"edit","timestamp":1701290776739},{"id":"WjnX.ipynb","source":"edit","timestamp":1701290801764},{"id":"YqMc.ipynb","source":"Insert Cell","timestamp":1701290827756},{"id":"IT56.ipynb","source":"Insert Cell","timestamp":1701290853764},{"id":"7wfY.ipynb","source":"Insert Cell","timestamp":1701290882940},{"id":"Rmzt.ipynb","source":"Insert Cell","timestamp":1701290902525},{"id":"BhMV.ipynb","source":"Insert Cell","timestamp":1701290945673},{"id":"i0GU.ipynb","source":"Insert Cell","timestamp":1701290971509},{"id":"lqev.ipynb","source":"Insert Cell","timestamp":1701290988298},{"id":"Tu4e.ipynb","source":"Insert Cell","timestamp":1701291198676},{"id":"7eZP.ipynb","source":"Update Cell Metadata","timestamp":1701292484797},{"id":"ki12.ipynb","source":"Update Cell Metadata","timestamp":1701292497585},{"id":"z5uz.ipynb","source":"Insert Cell","timestamp":1701292598598},{"id":"4Mwu.ipynb","source":"Insert Cell","timestamp":1701294091794},{"id":"3sWq.ipynb","source":"Insert Cell","timestamp":1701294105714},{"id":"UG9E.ipynb","timestamp":1701308919266},{"id":"Lxlu.ipynb","source":"edit","timestamp":1701309727528},{"id":"EI9e.ipynb","source":"Insert Cell","timestamp":1701312958437},{"id":"RFmD.ipynb","source":"Insert Cell","timestamp":1701313060030},{"id":"qp70.ipynb","source":"Insert Cell","timestamp":1701314387205},{"id":"kgee.ipynb","source":"Insert Cell","timestamp":1701314541387},{"id":"g34j.ipynb","source":"Insert Cell","timestamp":1701314639228},{"id":"xu9L.ipynb","source":"Insert Cell","timestamp":1701315605380},{"id":"OIzd.ipynb","source":"Insert Cell","timestamp":1701315619976},{"id":"rWrA.ipynb","source":"Insert Cell","timestamp":1701316748821},{"id":"tDZN.ipynb","source":"edit","timestamp":1701317741569},{"id":"jbnZ.ipynb","source":"Insert Cell","timestamp":1701319008376},{"id":"b3HD.ipynb","source":"Insert Cell","timestamp":1701319022532},{"id":"52p4.ipynb","timestamp":1701368587749},{"id":"Pg0U.ipynb","source":"edit","timestamp":1701390699455},{"id":"W20d.ipynb","source":"edit","timestamp":1701399007612},{"id":"RcSW.ipynb","timestamp":1701405473466},{"id":"by2N.ipynb","timestamp":1701405895381},{"id":"lnLN.ipynb","timestamp":1702176652294}]}